transcarread/__init__.py
transcarread/plots.py
transcarread-1.1.0.data/scripts/PlotTranscarInput.py
transcarread-1.1.0.data/scripts/transcar2excitationrates.py
transcarread-1.1.0.data/scripts/transcar2isr.py
transcarread-1.1.0.dist-info/DESCRIPTION.rst
transcarread-1.1.0.dist-info/METADATA
transcarread-1.1.0.dist-info/RECORD
transcarread-1.1.0.dist-info/WHEEL
transcarread-1.1.0.dist-info/metadata.json
transcarread-1.1.0.dist-info/top_level.txt
