Metadata-Version: 2.0
Name: transcarread
Version: 1.1.0
Summary: read and plot Transcar 1-D particle precipitation ionospheric model.
Home-page: https://github.com/scivision/transcarrread
Author: Michael Hirsch, Ph.D.
Author-email: UNKNOWN
License: UNKNOWN
Platform: UNKNOWN
Classifier: Development Status :: 4 - Beta
Classifier: Environment :: Console
Classifier: Intended Audience :: Science/Research
Classifier: Operating System :: OS Independent
Classifier: Programming Language :: Python :: 3
Classifier: Topic :: Scientific/Engineering :: Atmospheric Science
Requires-Python: >=3.6
Requires-Dist: gridaurora
Requires-Dist: numpy
Requires-Dist: python-dateutil
Requires-Dist: pytz
Requires-Dist: sciencedates
Requires-Dist: scipy
Requires-Dist: xarray
Provides-Extra: plot
Requires-Dist: matplotlib; extra == 'plot'
Requires-Dist: seaborn; extra == 'plot'
Provides-Extra: tests
Requires-Dist: coveralls; extra == 'tests'
Requires-Dist: nose; extra == 'tests'
Requires-Dist: pytest; extra == 'tests'
